{
  "type": "Feature",
  "properties": {
    "gn:country":"AD",
    "gn:fcode":"PPL",
    "gn:population":0,
    "iso:country":"AD",
    "qs_pg:aaroncc":"AD",
    "qs_pg:gn_country":"AD",
    "qs_pg:gn_fcode":"PPL",
    "qs_pg:gn_pop":0,
    "qs_pg:name":"Mas de Ribafeta",
    "qs_pg:name_adm0":"Andorra",
    "qs_pg:name_adm1":"La Massana",
    "qs_pg:photos":222,
    "qs_pg:photos_1k":45,
    "qs_pg:photos_9k":1,
    "qs_pg:photos_9r":4,
    "qs_pg:photos_all":222,
    "qs_pg:photos_sr":4,
    "qs_pg:pop_sr":0,
    "qs_pg:qs_pg_placetype":"locality",
    "qs_pg:qs_pg_placetype_gp":"Town",
    "qs_pg:woe_adm0":23424744,
    "woe:adm0_id":23424744,
    "woe:name_adm0":"Andorra",
    "woe:name_adm1":"La Massana",
    "woe:placetype":"Town",
    "wof:name":"Mas de Ribafeta",
    "wof:placetype":"locality"
},
  "geometry": {"coordinates":[1.48837,42.56936],"type":"Point"}
}