{
  "type": "Feature",
  "properties": {
    "gn:gn_country":"AD",
    "gn:gn_fcode":"PPL",
    "gn:gn_pop":2363,
    "gn:population":2363,
    "iso:country":"AD",
    "name:cat_x_preferred":[
        "El Pas de la Casa"
    ],
    "name:deu_x_preferred":[
        "El Pas de la Casa"
    ],
    "name:eng_x_preferred":[
        "El Pas de la Casa"
    ],
    "name:fas_x_preferred":[
        "\u067e\u0627\u0633 \u062f\u0647 \u0644\u0627 \u06a9\u0627\u0633\u0627"
    ],
    "name:fra_x_preferred":[
        "Pas de la Case"
    ],
    "name:ita_x_preferred":[
        "Pas de la Casa"
    ],
    "name:jpn_x_preferred":[
        "\u30d1\u30b9\u30fb\u30c0\u30fb\u30e9\u30fb\u30ab\u30b6"
    ],
    "name:lit_x_preferred":[
        "El Pas de la Kasa"
    ],
    "name:lmo_x_preferred":[
        "Pas de la Casa"
    ],
    "name:nld_x_preferred":[
        "El Pas de la Casa"
    ],
    "name:nob_x_preferred":[
        "Pas de la Casa"
    ],
    "name:oci_x_preferred":[
        "El Pas de la Casa"
    ],
    "name:pol_x_preferred":[
        "Pas de la Casa"
    ],
    "name:por_x_preferred":[
        "Pas de la Casa"
    ],
    "name:rus_x_preferred":[
        "\u041f\u0430\u0441 \u0434\u0435 \u043b\u0430 \u041a\u0430\u0441\u0430"
    ],
    "name:spa_x_preferred":[
        "El Pas de la Casa"
    ],
    "name:sqi_x_preferred":[
        "Pas De La Casa"
    ],
    "name:srp_x_preferred":[
        "\u041f\u0430\u0441 \u0434\u0435 \u043b\u0430 \u041a\u0430\u0441\u0430"
    ],
    "name:swe_x_preferred":[
        "Pas de la Casa"
    ],
    "name:tur_x_preferred":[
        "Pas de la Casa"
    ],
    "name:ukr_x_preferred":[
        "\u041f\u0430\u0441-\u0434\u0435-\u043b\u0430-\u041a\u0430\u0441\u0430"
    ],
    "name:vol_x_preferred":[
        "Pas de la Casa"
    ],
    "qs_pg:aaroncc":"AD",
    "qs_pg:gn_country":"AD",
    "qs_pg:gn_fcode":"PPL",
    "qs_pg:gn_pop":2363,
    "qs_pg:name":"Pas de la Case",
    "qs_pg:name_adm0":"France",
    "qs_pg:name_adm1":"Languedoc-Roussillon",
    "qs_pg:photos":194,
    "qs_pg:photos_1k":39,
    "qs_pg:photos_9k":1,
    "qs_pg:photos_9r":4,
    "qs_pg:photos_all":194,
    "qs_pg:photos_sr":4,
    "qs_pg:pop_sr":4,
    "qs_pg:qs_pg_placetype":"locality",
    "qs_pg:qs_pg_placetype_gp":"Town",
    "qs_pg:woe_adm0":23424819,
    "woe:adm0_id":23424819,
    "woe:name_adm0":"France",
    "woe:name_adm1":"Languedoc-Roussillon",
    "woe:placetype":"Town",
    "wof:name":"Pas de la Case",
    "wof:placetype":"locality",
    "wof:population":2363
},
  "geometry": {"coordinates":[1.73361,42.54277],"type":"Point"}
}