{
  "type": "Feature",
  "properties": {
    "gn:admin1_code":"04",
    "gn:asciiname":"Escas",
    "gn:country_code":"AD",
    "gn:dem":1331,
    "gn:feature_class":"P",
    "gn:feature_code":"PPL",
    "gn:name":"Esc\u00e0s",
    "gn:population":0,
    "gn:timezone":"Europe/Andorra",
    "iso:country":"AD",
    "name:und_x_variant":[
        "Esc\u00e0s"
    ],
    "wof:name":"Escas",
    "wof:placetype":"locality"
},
  "geometry": {"coordinates":[1.50895,42.54643],"type":"Point"}
}