{
  "type": "Feature",
  "properties": {
    "gn:gn_country":"AD",
    "gn:gn_fcode":"PPL",
    "gn:gn_pop":594,
    "gn:population":594,
    "iso:country":"AD",
    "qs_pg:aaroncc":"AD",
    "qs_pg:gn_country":"AD",
    "qs_pg:gn_fcode":"PPL",
    "qs_pg:gn_pop":594,
    "qs_pg:name":"L'Aldosa",
    "qs_pg:name_adm0":"Andorra",
    "qs_pg:name_adm1":"La Massana",
    "qs_pg:photos":81,
    "qs_pg:photos_1k":16,
    "qs_pg:photos_9k":1,
    "qs_pg:photos_9r":3,
    "qs_pg:photos_all":81,
    "qs_pg:photos_sr":3,
    "qs_pg:pop_sr":2,
    "qs_pg:qs_pg_placetype":"locality",
    "qs_pg:qs_pg_placetype_gp":"Town",
    "qs_pg:woe_adm0":23424744,
    "woe:adm0_id":23424744,
    "woe:name_adm0":"Andorra",
    "woe:name_adm1":"La Massana",
    "woe:placetype":"Town",
    "wof:name":"L'Aldosa",
    "wof:placetype":"locality",
    "wof:population":594
},
  "geometry": {"coordinates":[1.52289,42.54391],"type":"Point"}
}