{
  "type": "Feature",
  "properties": {
    "gn:admin1_code":"02",
    "gn:asciiname":"Incles",
    "gn:country_code":"AD",
    "gn:dem":1747,
    "gn:feature_class":"P",
    "gn:feature_code":"PPL",
    "gn:name":"Incles",
    "gn:population":0,
    "gn:timezone":"Europe/Andorra",
    "iso:country":"AD",
    "name:ast_x_preferred":[
        "Incles"
    ],
    "name:cat_x_preferred":[
        "Incles"
    ],
    "name:fas_x_preferred":[
        "\u0627\u06cc\u0646\u06a9\u0644\u0633"
    ],
    "name:fin_x_preferred":[
        "Incles"
    ],
    "name:fra_x_preferred":[
        "Incles"
    ],
    "name:ita_x_preferred":[
        "Incles"
    ],
    "name:lmo_x_preferred":[
        "Incles"
    ],
    "name:nld_x_preferred":[
        "Incles"
    ],
    "name:pol_x_preferred":[
        "Incles"
    ],
    "name:spa_x_preferred":[
        "Incles"
    ],
    "name:sqi_x_preferred":[
        "Incles"
    ],
    "wof:name":"Incles",
    "wof:placetype":"locality"
},
  "geometry": {"coordinates":[1.66267,42.58285],"type":"Point"}
}