{
  "type": "Feature",
  "properties": {
    "gn:gn_country":"AD",
    "gn:gn_fcode":"PPL",
    "gn:gn_pop":0,
    "iso:country":"AD",
    "name:bar_x_preferred":[
        "Meritxell"
    ],
    "name:cat_x_preferred":[
        "Meritxell"
    ],
    "name:deu_x_preferred":[
        "Meritxell"
    ],
    "name:fas_x_preferred":[
        "\u0645\u0631\u06cc\u062a\u0634\u0644"
    ],
    "name:fin_x_preferred":[
        "Meritxell"
    ],
    "name:fra_x_preferred":[
        "Meritxell"
    ],
    "name:ita_x_preferred":[
        "Meritxell"
    ],
    "name:lmo_x_preferred":[
        "Meritxell"
    ],
    "name:nor_x_preferred":[
        "Meritxell"
    ],
    "name:oci_x_preferred":[
        "Meritxell"
    ],
    "name:sqi_x_preferred":[
        "Meritxell"
    ],
    "name:unk_x_variant":[
        "Santuari de Meritxell"
    ],
    "name:vol_x_preferred":[
        "Meritxell"
    ],
    "qs_pg:aaroncc":"AD",
    "qs_pg:gn_country":"AD",
    "qs_pg:gn_fcode":"PPL",
    "qs_pg:gn_pop":0,
    "qs_pg:name":"Meritxell",
    "qs_pg:name_adm0":"Andorra",
    "qs_pg:name_adm1":"Canillo",
    "qs_pg:photos":237,
    "qs_pg:photos_1k":48,
    "qs_pg:photos_9k":1,
    "qs_pg:photos_9r":4,
    "qs_pg:photos_all":237,
    "qs_pg:photos_sr":4,
    "qs_pg:pop_sr":0,
    "qs_pg:qs_pg_placetype":"locality",
    "qs_pg:qs_pg_placetype_gp":"Town",
    "qs_pg:woe_adm0":23424744,
    "woe:adm0_id":23424744,
    "woe:name_adm0":"Andorra",
    "woe:name_adm1":"Canillo",
    "woe:placetype":"Town",
    "wof:name":"Meritxell",
    "wof:placetype":"locality"
},
  "geometry": {"coordinates":[1.59087,42.55403],"type":"Point"}
}